README.md
setup.py
ediri_ovh/__init__.py
ediri_ovh/_utilities.py
ediri_ovh/get_installation_templates.py
ediri_ovh/get_server.py
ediri_ovh/get_servers.py
ediri_ovh/get_vrack_networks.py
ediri_ovh/outputs.py
ediri_ovh/provider.py
ediri_ovh/pulumi-plugin.json
ediri_ovh/py.typed
ediri_ovh.egg-info/PKG-INFO
ediri_ovh.egg-info/SOURCES.txt
ediri_ovh.egg-info/dependency_links.txt
ediri_ovh.egg-info/not-zip-safe
ediri_ovh.egg-info/requires.txt
ediri_ovh.egg-info/top_level.txt
ediri_ovh/cloudproject/__init__.py
ediri_ovh/cloudproject/_inputs.py
ediri_ovh/cloudproject/container_registry.py
ediri_ovh/cloudproject/container_registry_user.py
ediri_ovh/cloudproject/database.py
ediri_ovh/cloudproject/failover_ip_attach.py
ediri_ovh/cloudproject/get_capabilities_container_filter.py
ediri_ovh/cloudproject/get_capabilities_container_registry.py
ediri_ovh/cloudproject/get_container_registries.py
ediri_ovh/cloudproject/get_container_registry.py
ediri_ovh/cloudproject/get_container_registry_users.py
ediri_ovh/cloudproject/get_failover_ip_attach.py
ediri_ovh/cloudproject/get_kube.py
ediri_ovh/cloudproject/get_kube_ip_restrictions.py
ediri_ovh/cloudproject/get_kube_node_pool.py
ediri_ovh/cloudproject/get_kube_node_pool_nodes.py
ediri_ovh/cloudproject/get_kube_nodes.py
ediri_ovh/cloudproject/get_kube_oidc.py
ediri_ovh/cloudproject/get_m3db_namespace.py
ediri_ovh/cloudproject/get_m3db_namespaces.py
ediri_ovh/cloudproject/get_m3db_user.py
ediri_ovh/cloudproject/get_mongo_db_user.py
ediri_ovh/cloudproject/get_open_search_pattern.py
ediri_ovh/cloudproject/get_open_search_patterns.py
ediri_ovh/cloudproject/get_open_search_user.py
ediri_ovh/cloudproject/get_redis_user.py
ediri_ovh/cloudproject/get_region.py
ediri_ovh/cloudproject/get_regions.py
ediri_ovh/cloudproject/get_user.py
ediri_ovh/cloudproject/get_user_s3_credential.py
ediri_ovh/cloudproject/get_user_s3_credentials.py
ediri_ovh/cloudproject/get_user_s3_policy.py
ediri_ovh/cloudproject/get_users.py
ediri_ovh/cloudproject/kube.py
ediri_ovh/cloudproject/kube_ip_restrictions.py
ediri_ovh/cloudproject/kube_node_pool.py
ediri_ovh/cloudproject/kube_oidc.py
ediri_ovh/cloudproject/network_private.py
